{
    "Observation (1)": {
        "iss_cords": [
            [
                42.4633,
                27.237
            ],
            [
                42.4986,
                27.306
            ],
            [
                42.5337,
                27.376
            ],
            [
                42.5689,
                27.445
            ],
            [
                42.6039,
                27.515
            ],
            [
                42.639,
                27.584
            ],
            [
                42.674,
                27.654
            ],
            [
                42.7089,
                27.724
            ],
            [
                42.7438,
                27.794
            ],
            [
                42.7786,
                27.864
            ],
            [
                42.8134,
                27.934
            ],
            [
                42.8482,
                28.004
            ],
            [
                42.8829,
                28.074
            ],
            [
                42.9175,
                28.144
            ],
            [
                42.9521,
                28.215
            ],
            [
                42.9866,
                28.285
            ],
            [
                43.0211,
                28.356
            ],
            [
                43.0556,
                28.426
            ],
            [
                43.09,
                28.497
            ],
            [
                43.1244,
                28.568
            ],
            [
                43.1587,
                28.638
            ],
            [
                43.1929,
                28.709
            ],
            [
                43.2271,
                28.78
            ],
            [
                43.2613,
                28.851
            ],
            [
                43.2954,
                28.923
            ],
            [
                43.3294,
                28.994
            ],
            [
                43.3634,
                29.065
            ]
        ],
        "observation_duration": 27,
        "observation_start": "2023-09-22 14:54:06",
        "observation_end": "2023-09-22 14:54:32"
    }
}